dcu/__init__.py
dcu/dcu.py
dcu-0.0.5.dist-info/METADATA
dcu-0.0.5.dist-info/WHEEL
dcu-0.0.5.dist-info/licenses/LICENSE
dcu-0.0.5.dist-info/RECORD
