Metadata-Version: 2.4
Name: dcu
Version: 0.0.5
Summary: The very coolest most bestest cool utility
Project-URL: Homepage, https://github.com/dwhenry3/CIS-314
Project-URL: Issues, https://github.com/dwhenry3/CS-314/issues
Author-email: Dane Henry <dane@dwhenry.com>
License-File: LICENSE
Classifier: License :: OSI Approved :: MIT License
Classifier: Operating System :: OS Independent
Classifier: Programming Language :: Python :: 3
Requires-Python: >=3.8
Requires-Dist: beautifulsoup4>4.12.3
Requires-Dist: requests
